{"version":1,"resource":"file:///h%3A/School/UVIC%20FALL%202025/SENG265/lab4/lab-04/q_word_freq.c","entries":[{"id":"yFm2.c","timestamp":1759431086208},{"id":"KlYk.c","timestamp":1759431306027},{"id":"bWHK.c","timestamp":1759431330788},{"id":"EYLy.c","timestamp":1759431358462},{"id":"GlEl.c","timestamp":1759431609871},{"id":"xUEx.c","timestamp":1759431783156},{"id":"ZrcN.c","timestamp":1759431824844},{"id":"RCuV.c","timestamp":1759431853401},{"id":"xPZM.c","timestamp":1759431930112},{"id":"Tgt6.c","timestamp":1759431972402},{"id":"4nQc.c","timestamp":1759431994644},{"id":"Hh0M.c","timestamp":1759432028124},{"id":"Ojl2.c","timestamp":1759432243185},{"id":"ioCw.c","timestamp":1759432264982},{"id":"6kub.c","timestamp":1759432302737},{"id":"78Bw.c","timestamp":1759432357662},{"id":"qjfI.c","timestamp":1759432390678},{"id":"DrU1.c","timestamp":1759432427306},{"id":"B3eg.c","timestamp":1759432514312},{"id":"m69s.c","timestamp":1759432525192},{"id":"owtl.c","timestamp":1759432553740},{"id":"wUc1.c","timestamp":1759432640678},{"id":"jr4o.c","timestamp":1759432671760},{"id":"zWUZ.c","timestamp":1759432970148},{"id":"UCyf.c","timestamp":1759433116071},{"id":"H9lk.c","timestamp":1759433132686},{"id":"uDjH.c","timestamp":1759433176953},{"id":"yxTL.c","timestamp":1759433198682},{"id":"1o7r.c","timestamp":1759433400872},{"id":"YT1e.c","timestamp":1759433419823},{"id":"SsYs.c","timestamp":1759433456805},{"id":"20o7.c","timestamp":1759434353029},{"id":"zd9i.c","timestamp":1759434392156},{"id":"tIYN.c","timestamp":1759434420027},{"id":"kRwC.c","timestamp":1759434444387},{"id":"Bbiw.c","timestamp":1759434479325},{"id":"4KS4.c","timestamp":1759434510531},{"id":"XWdv.c","timestamp":1759434601265},{"id":"9heR.c","timestamp":1759434913618},{"id":"TOVf.c","timestamp":1759435009467},{"id":"iWcq.c","timestamp":1759435122999},{"id":"up4g.c","timestamp":1759435168605},{"id":"RQkk.c","timestamp":1759435200031},{"id":"rFng.c","timestamp":1759435645970},{"id":"EByL.c","timestamp":1759435666191},{"id":"xe7K.c","timestamp":1759435683081},{"id":"bB4Q.c","timestamp":1759435806600},{"id":"HWMm.c","timestamp":1759436034064},{"id":"b1Ov.c","timestamp":1759436241182},{"id":"5bXR.c","timestamp":1759436270084}]}